convcompose.py
gencompose.py
toXcompose.py
gen_compose-1.2.0.dist-info/entry_points.txt
gen_compose-1.2.0.dist-info/WHEEL
gen_compose-1.2.0.dist-info/METADATA
gen_compose-1.2.0.dist-info/RECORD
