Metadata-Version: 2.1
Name: gen-compose
Version: 1.2.0
Summary: Key generator for macos keybinding system
Home-page: https://github.com/Granitosaurus/macos-compose
License: GPL-3.0-or-later
Keywords: macos,compose,keymap
Author: Granitosaurus
Author-email: wraptile@pm.me
Requires-Python: >=3.6,<4.0
Classifier: Development Status :: 4 - Beta
Classifier: License :: OSI Approved :: GNU General Public License v3 or later (GPLv3+)
Classifier: Programming Language :: Python :: 3
Classifier: Programming Language :: Python :: 3.6
Classifier: Programming Language :: Python :: 3.7
Classifier: Programming Language :: Python :: 3.8
Classifier: Programming Language :: Python :: 3.9
Classifier: Programming Language :: Python :: 3.10
Classifier: Topic :: System :: Hardware
Classifier: Topic :: Utilities
Requires-Dist: click (>=7.1.2,<8.0.0)
Requires-Dist: pyyaml (>=5.3.1,<6.0.0)
Project-URL: Repository, https://github.com/Granitosaurus/macos-compose
